README.md
setup.py
zhei_init/__init__.py
zhei_init/env.py
zhei_init/utils.py
zhei_init.egg-info/PKG-INFO
zhei_init.egg-info/SOURCES.txt
zhei_init.egg-info/dependency_links.txt
zhei_init.egg-info/entry_points.txt
zhei_init.egg-info/requires.txt
zhei_init.egg-info/top_level.txt